image_similarity_measures/__init__.py
image_similarity_measures/evaluate.py
image_similarity_measures/quality_metrics.py
image_similarity_measures-0.3.5.dist-info/LICENSE
image_similarity_measures-0.3.5.dist-info/METADATA
image_similarity_measures-0.3.5.dist-info/WHEEL
image_similarity_measures-0.3.5.dist-info/entry_points.txt
image_similarity_measures-0.3.5.dist-info/top_level.txt
image_similarity_measures-0.3.5.dist-info/RECORD
