Metadata-Version: 2.1
Name: image-similarity-measures
Version: 0.3.5
Summary: Evaluation metrics to assess the similarity between two images.
Home-page: https://github.com/up42/image-similarity-measures
Author: UP42
Author-email: support@up42.com
License: MIT
Platform: UNKNOWN
Classifier: Programming Language :: Python :: 3
Classifier: License :: OSI Approved :: MIT License
Classifier: Operating System :: OS Independent
Classifier: Intended Audience :: Science/Research
Classifier: Development Status :: 5 - Production/Stable
Requires-Python: >=3.6, <3.10
